log_viewer/__init__.py
log_viewer/admin.py
log_viewer/apps.py
log_viewer/models.py
log_viewer/tests.py
log_viewer/urls.py
log_viewer/utils.py
log_viewer/views.py
log_viewer/migrations/__init__.py
log_viewer/static/log_viewer/css/demo.css
log_viewer/static/log_viewer/css/material-dashboard.min.css
log_viewer/static/log_viewer/css/nucleo-icons.css
log_viewer/static/log_viewer/css/nucleo-svg.css
log_viewer/static/log_viewer/img/sidebar-1.jpg
log_viewer/static/log_viewer/js/42d5adcbca.js
log_viewer/static/log_viewer/js/bootstrap-material-design.min.js
log_viewer/static/log_viewer/js/bootstrap.min.js
log_viewer/static/log_viewer/js/jquery.min.js
log_viewer/static/log_viewer/js/material-dashboard.min.js
log_viewer/static/log_viewer/js/perfect-scrollbar.jquery.min.js
log_viewer/static/log_viewer/js/perfect-scrollbar.min.js
log_viewer/static/log_viewer/js/popper.min.js
log_viewer/static/log_viewer/js/smooth-scrollbar.min.js
log_viewer/templates/base/main_manager.html
log_viewer/templates/log_viewer/log_body.html
log_viewer/templates/log_viewer/log_home.html
django_simple_log_viewer-1.1.1.dist-info/LICENSE
django_simple_log_viewer-1.1.1.dist-info/METADATA
django_simple_log_viewer-1.1.1.dist-info/WHEEL
django_simple_log_viewer-1.1.1.dist-info/top_level.txt
django_simple_log_viewer-1.1.1.dist-info/RECORD
