Metadata-Version: 2.1
Name: django-simple-log-viewer
Version: 1.1.1
Summary: A Django app to view project logs.
Home-page: https://github.com/yusufoguntola/django-simple-log-viewer
Author: Yusuf Oguntola
Author-email: yusuf.oguntola@gmail.com
License: MIT License
Platform: UNKNOWN
Classifier: Environment :: Web Environment
Classifier: Framework :: Django
Classifier: Framework :: Django :: 1.5
Classifier: Intended Audience :: Developers
Classifier: License :: OSI Approved :: MIT License
Classifier: Operating System :: OS Independent
Classifier: Programming Language :: Python
Classifier: Programming Language :: Python :: 2
Classifier: Programming Language :: Python :: 3
Classifier: Topic :: Internet :: WWW/HTTP
Classifier: Topic :: Internet :: WWW/HTTP :: Dynamic Content
Requires-Python: >=2.6
License-File: LICENSE
